population_analysis/__init__.py
population_analysis/consts.py
population_analysis/figures.py
population_analysis/util.py
population_analysis/plotting/__init__.py
population_analysis/plotting/matrix_transform_plots.py
population_analysis/plotting/quantify_density_plots.py
population_analysis/plotting/time_trajectory_plots.py
population_analysis/plotting/debugging/__init__.py
population_analysis/plotting/debugging/debugging_alon_compare.py
population_analysis/plotting/debugging/debugging_angle_distances.py
population_analysis/plotting/debugging/debugging_latency_distance.py
population_analysis/plotting/debugging/debugging_rp_extra_dist_baseline.py
population_analysis/plotting/debugging/debugging_rp_peri_calculation.py
population_analysis/plotting/debugging/debugging_rp_peri_firingrates.py
population_analysis/plotting/debugging/debugging_rp_peri_units_firingrates.py
population_analysis/plotting/debugging/debugging_timewindow_firingrate_and_dist.py
population_analysis/plotting/debugging/debugging_unit_trials.py
population_analysis/plotting/debugging/josh/__init__.py
population_analysis/plotting/debugging/josh/debugging_josh_distances.py
population_analysis/plotting/debugging/josh/debugging_josh_unit_firingrates.py
population_analysis/plotting/distance/__init__.py
population_analysis/plotting/distance/distance_multi_view.py
population_analysis/plotting/distance/distance_probe_offset_binned.py
population_analysis/plotting/distance/distance_rpe_v_rpe_cdf_plots.py
population_analysis/plotting/distance/distance_rpp_rpe_errorbars_plots.py
population_analysis/plotting/distance/distance_rpp_rpe_rs_plots.py
population_analysis/plotting/distance/distance_verifiation_by_density_rpe_v_rpe_plots.py
population_analysis/plotting/distance/fraction_distance_significant.py
population_analysis/plotting/distance/todo_distance_by_block_plots.py
population_analysis/plotting/distance/todo_distance_plots.py
population_analysis/plotting/figures/__init__.py
population_analysis-1.0.0.dist-info/METADATA
population_analysis-1.0.0.dist-info/WHEEL
population_analysis-1.0.0.dist-info/top_level.txt
population_analysis-1.0.0.dist-info/RECORD
