Metadata-Version: 2.1
Name: population-analysis
Version: 1.0.0
Summary: Analysis code for a papers population analysis
Author: Spencer Hanson
Keywords: neuroscience,nwb,tools,science
Classifier: Programming Language :: Python :: 3
Requires-Dist: h5py
Requires-Dist: numpy
Requires-Dist: scipy
Requires-Dist: scikit-learn
Requires-Dist: jupyterlab
Requires-Dist: ipympl
Requires-Dist: matplotlib
Requires-Dist: simply-nwb
Requires-Dist: pynwb
Requires-Dist: pendulum
Requires-Dist: numexpr
Requires-Dist: llvmlite
Requires-Dist: numba
Requires-Dist: graph-judge (==0.0.6)
Requires-Dist: google-api-python-client
Requires-Dist: google-auth-httplib2
Requires-Dist: google-auth-oauthlib
Requires-Dist: twine
